python_kanban/__init__.py
python_kanban/app.py
python_kanban/models.py
python_kanban/views/__init__.py
python_kanban/views/add_task_view.py
python_kanban/views/delete_task_view.py
python_kanban/views/edit_tasks_view.py
python_kanban/views/list_tasks_view.py
python_kanban/views/no_tasks_view.py
python_kanban/views/status_container_view.py
python_kanban-0.2.0.dist-info/entry_points.txt
python_kanban-0.2.0.dist-info/LICENSE
python_kanban-0.2.0.dist-info/WHEEL
python_kanban-0.2.0.dist-info/METADATA
python_kanban-0.2.0.dist-info/RECORD
