Metadata-Version: 2.1
Name: python-kanban
Version: 0.2.0
Summary: Text-based interface for a Kanban board in pure Python
Home-page: https://github.com/fillipe-gsm/python-kanban
License: MIT
Author: Fillipe Goulart
Author-email: fillipe.gsm@tutanota.com
Requires-Python: >=3.7,<4.0
Classifier: License :: OSI Approved :: MIT License
Classifier: Programming Language :: Python :: 3
Classifier: Programming Language :: Python :: 3.7
Classifier: Programming Language :: Python :: 3.8
Classifier: Programming Language :: Python :: 3.9
Requires-Dist: dynaconf (>=3.1.4,<4.0.0)
Requires-Dist: peewee (>=3.14.4,<4.0.0)
Requires-Dist: prompt-toolkit (>=3.0.18,<4.0.0)
Project-URL: Repository, https://github.com/fillipe-gsm/python-kanban
